MANIFEST.in
README.rst
setup.py
italian_csv_type_prediction/__init__.py
italian_csv_type_prediction/__version__.py
italian_csv_type_prediction/translate_types.py
italian_csv_type_prediction.egg-info/PKG-INFO
italian_csv_type_prediction.egg-info/SOURCES.txt
italian_csv_type_prediction.egg-info/dependency_links.txt
italian_csv_type_prediction.egg-info/requires.txt
italian_csv_type_prediction.egg-info/top_level.txt
italian_csv_type_prediction/column_types/__init__.py
italian_csv_type_prediction/column_types/any_type.py
italian_csv_type_prediction/column_types/column_type_predictor.py
italian_csv_type_prediction/column_types/numeric_id_type.py
italian_csv_type_prediction/column_types/set_type_column.py
italian_csv_type_prediction/column_types/single_type_column.py
italian_csv_type_prediction/dataframe_generators/__init__.py
italian_csv_type_prediction/dataframe_generators/simple_dataset_generator.py
italian_csv_type_prediction/datasets/Address.json.gz
italian_csv_type_prediction/datasets/BiologicalSex.json.gz
italian_csv_type_prediction/datasets/Boolean.json.gz
italian_csv_type_prediction/datasets/CAP.json.gz
italian_csv_type_prediction/datasets/CodiceCatasto.json.gz
italian_csv_type_prediction/datasets/CodiceFiscale.json.gz
italian_csv_type_prediction/datasets/Country.json.gz
italian_csv_type_prediction/datasets/CountryCode.json.gz
italian_csv_type_prediction/datasets/Document.json.gz
italian_csv_type_prediction/datasets/GenericCAP.json.gz
italian_csv_type_prediction/datasets/IVA.json.gz
italian_csv_type_prediction/datasets/Municipality.json.gz
italian_csv_type_prediction/datasets/Name.json.gz
italian_csv_type_prediction/datasets/Plate.json.gz
italian_csv_type_prediction/datasets/ProvinceCode.json.gz
italian_csv_type_prediction/datasets/Region.json.gz
italian_csv_type_prediction/datasets/String.json.gz
italian_csv_type_prediction/datasets/Surname.json.gz
italian_csv_type_prediction/datasets/__init__.py
italian_csv_type_prediction/datasets/address_starters.json.gz
italian_csv_type_prediction/datasets/currency_starters.json.gz
italian_csv_type_prediction/datasets/date.json.gz
italian_csv_type_prediction/datasets/email.json.gz
italian_csv_type_prediction/datasets/euro.json.gz
