Metadata-Version: 2.1
Name: italian-csv-type-prediction
Version: 1.1.65
Summary: Attempt at predicting common types in CSVs about Italian people and places using Spacy NLP tool.
Home-page: https://github.com/LucaCappelletti94/italian_csv_type_prediction
Author: LucaCappelletti94
Author-email: cappelletti.luca94@gmail.com
License: MIT
Platform: UNKNOWN
Classifier: Development Status :: 3 - Alpha
Classifier: License :: OSI Approved :: MIT License
Classifier: Programming Language :: Python :: 3
Requires-Python: >3.5.2
Provides-Extra: test
